{"crs": {"type": "name", "properties": {"name": "urn:ogc:def:crs:OGC:1.3:CRS84"}}, "type": "FeatureCollection", "features": [{"geometry": {"type": "Polygon", "coordinates": [[[-73.906457, 40.821715], [-73.908418, 40.822181], [-73.907741, 40.823815], [-73.91131, 40.824849], [-73.911694, 40.827759], [-73.90896, 40.830226], [-73.905531, 40.829104], [-73.904506, 40.830625], [-73.902275, 40.829637], [-73.90508, 40.827114], [-73.904293, 40.82692], [-73.904922, 40.825287], [-73.906457, 40.821715]]]}, "type": "Feature", "properties": {"nabe": "Morrisania-Melrose", "nabgeoid10": "36005018500", "geoname": "Census Tract 185, Bronx County, New York", "geoid": "36005018500"}}]}