{"crs": {"type": "name", "properties": {"name": "urn:ogc:def:crs:OGC:1.3:CRS84"}}, "type": "FeatureCollection", "features": [{"geometry": {"type": "Polygon", "coordinates": [[[-73.865746, 40.821012], [-73.870501, 40.820364], [-73.871546, 40.824826], [-73.869842, 40.824923], [-73.865746, 40.821012]]]}, "type": "Feature", "properties": {"nabe": "Soundview-Castle Hill-Clason Point-Harding Park", "nabgeoid10": "36005004600", "geoname": "Census Tract 46, Bronx County, New York", "geoid": "36005004600"}}]}