{"crs": {"type": "name", "properties": {"name": "urn:ogc:def:crs:OGC:1.3:CRS84"}}, "type": "FeatureCollection", "features": [{"geometry": {"type": "Polygon", "coordinates": [[[-73.950493, 40.659405], [-73.956725, 40.659017], [-73.957044, 40.661965], [-73.9537, 40.662174], [-73.95081, 40.662354], [-73.950493, 40.659405]]]}, "type": "Feature", "properties": {"nabe": "Prospect Lefferts Gardens-Wingate", "nabgeoid10": "36047080000", "geoname": "Census Tract 800, Kings County, New York", "geoid": "36047080000"}}]}