{"crs": {"type": "name", "properties": {"name": "urn:ogc:def:crs:OGC:1.3:CRS84"}}, "type": "FeatureCollection", "features": [{"geometry": {"type": "Polygon", "coordinates": [[[-73.956859, 40.710452], [-73.955476, 40.712266], [-73.95434, 40.714072], [-73.953583, 40.71407], [-73.949372, 40.714067], [-73.948655, 40.709725], [-73.95083, 40.709143], [-73.954735, 40.710595], [-73.955498, 40.709949], [-73.956859, 40.710452]]]}, "type": "Feature", "properties": {"nabe": "North Side-South Side", "nabgeoid10": "36047051300", "geoname": "Census Tract 513, Kings County, New York", "geoid": "36047051300"}}]}