{"crs": {"type": "name", "properties": {"name": "urn:ogc:def:crs:OGC:1.3:CRS84"}}, "type": "FeatureCollection", "features": [{"geometry": {"type": "Polygon", "coordinates": [[[-73.874105, 40.683104], [-73.874566, 40.684955], [-73.875831, 40.684639], [-73.876681, 40.688088], [-73.874054, 40.689299], [-73.872739, 40.68541], [-73.872187, 40.683649], [-73.874105, 40.683104]]]}, "type": "Feature", "properties": {"nabe": "Cypress Hills-City Line", "nabgeoid10": "36047117602", "geoname": "Census Tract 1176.02, Kings County, New York", "geoid": "36047117602"}}]}