{"crs": {"type": "name", "properties": {"name": "urn:ogc:def:crs:OGC:1.3:CRS84"}}, "type": "FeatureCollection", "features": [{"geometry": {"type": "Polygon", "coordinates": [[[-73.905851, 40.694069], [-73.908799, 40.695845], [-73.912556, 40.697982], [-73.914061, 40.698838], [-73.911362, 40.701495], [-73.910578, 40.700998], [-73.911655, 40.699905], [-73.910982, 40.699536], [-73.905772, 40.69651], [-73.904425, 40.695671], [-73.905851, 40.694069]]]}, "type": "Feature", "properties": {"nabe": "Bushwick North", "nabgeoid10": "36047043900", "geoname": "Census Tract 439, Kings County, New York", "geoid": "36047043900"}}]}