{"crs": {"type": "name", "properties": {"name": "urn:ogc:def:crs:OGC:1.3:CRS84"}}, "type": "FeatureCollection", "features": [{"geometry": {"type": "Polygon", "coordinates": [[[-73.971217, 40.755193], [-73.973503, 40.752065], [-73.974449, 40.750766], [-73.977677, 40.752119], [-73.97837, 40.752416], [-73.976516, 40.754974], [-73.975807, 40.754678], [-73.974439, 40.756556], [-73.971217, 40.755193]]]}, "type": "Feature", "properties": {"nabe": "Turtle Bay-East Midtown", "nabgeoid10": "36061009200", "geoname": "Census Tract 92, New York County, New York", "geoid": "36061009200"}}]}