{"crs": {"type": "name", "properties": {"name": "urn:ogc:def:crs:OGC:1.3:CRS84"}}, "type": "FeatureCollection", "features": [{"geometry": {"type": "Polygon", "coordinates": [[[-73.997099, 40.747205], [-73.998972, 40.74463], [-74.004653, 40.747023], [-74.002785, 40.749592], [-73.997099, 40.747205]]]}, "type": "Feature", "properties": {"nabe": "Hudson Yards-Chelsea-Flat Iron-Union Square", "nabgeoid10": "36061009300", "geoname": "Census Tract 93, New York County, New York", "geoid": "36061009300"}}]}