{"crs": {"type": "name", "properties": {"name": "urn:ogc:def:crs:OGC:1.3:CRS84"}}, "type": "FeatureCollection", "features": [{"geometry": {"type": "Polygon", "coordinates": [[[-73.975598, 40.724283], [-73.980333, 40.726281], [-73.979906, 40.726866], [-73.978001, 40.729429], [-73.973291, 40.727434], [-73.975598, 40.724283]]]}, "type": "Feature", "properties": {"nabe": "Lower East Side", "nabgeoid10": "36061002800", "geoname": "Census Tract 28, New York County, New York", "geoid": "36061002800"}}]}