{"crs": {"type": "name", "properties": {"name": "urn:ogc:def:crs:OGC:1.3:CRS84"}}, "type": "FeatureCollection", "features": [{"geometry": {"type": "Polygon", "coordinates": [[[-73.811632, 40.703052], [-73.811529, 40.702273], [-73.816288, 40.702453], [-73.819386, 40.708425], [-73.819089, 40.708592], [-73.816416, 40.709865], [-73.813418, 40.709711], [-73.813059, 40.706978], [-73.812189, 40.707067], [-73.812012, 40.705945], [-73.811632, 40.703052]]]}, "type": "Feature", "properties": {"nabe": "Briarwood-Jamaica Hills", "nabgeoid10": "36081021400", "geoname": "Census Tract 214, Queens County, New York", "geoid": "36081021400"}}]}