{"crs": {"type": "name", "properties": {"name": "urn:ogc:def:crs:OGC:1.3:CRS84"}}, "type": "FeatureCollection", "features": [{"geometry": {"type": "Polygon", "coordinates": [[[-73.844277, 40.72763], [-73.843934, 40.726965], [-73.848082, 40.72573], [-73.849247, 40.72845], [-73.850253, 40.729655], [-73.845987, 40.730955], [-73.845707, 40.729501], [-73.844277, 40.72763]]]}, "type": "Feature", "properties": {"nabe": "Forest Hills", "nabgeoid10": "36081074100", "geoname": "Census Tract 741, Queens County, New York", "geoid": "36081074100"}}]}