{"crs": {"type": "name", "properties": {"name": "urn:ogc:def:crs:OGC:1.3:CRS84"}}, "type": "FeatureCollection", "features": [{"geometry": {"type": "Polygon", "coordinates": [[[-73.86583, 40.736643], [-73.866095, 40.737251], [-73.86704, 40.739572], [-73.867557, 40.741678], [-73.86241, 40.74289], [-73.860072, 40.738373], [-73.86583, 40.736643]]]}, "type": "Feature", "properties": {"nabe": "Corona", "nabgeoid10": "36081044302", "geoname": "Census Tract 443.02, Queens County, New York", "geoid": "36081044302"}}]}