{"crs": {"type": "name", "properties": {"name": "urn:ogc:def:crs:OGC:1.3:CRS84"}}, "type": "FeatureCollection", "features": [{"geometry": {"type": "Polygon", "coordinates": [[[-73.925399, 40.738111], [-73.919836, 40.737464], [-73.920447, 40.73485], [-73.922726, 40.734356], [-73.924492, 40.735393], [-73.931614, 40.736826], [-73.929946, 40.737536], [-73.92763, 40.738401], [-73.925399, 40.738111]]]}, "type": "Feature", "properties": {"nabe": "Hunters Point-Sunnyside-West Maspeth", "nabgeoid10": "36081018700", "geoname": "Census Tract 187, Queens County, New York", "geoid": "36081018700"}}]}